ovisbot/__init__.py
ovisbot/__main__.py
ovisbot/bot.py
ovisbot/cli.py
ovisbot/cog_manager.py
ovisbot/config.py
ovisbot/db_models.py
ovisbot/error_handling.py
ovisbot/events.py
ovisbot/exceptions.py
ovisbot/helpers.py
ovisbot/locale.py
ovisbot/locale/ovisbot.pot
ovisbot/locale/cy/LC_MESSAGES/ovisbot.mo
ovisbot/locale/cy/LC_MESSAGES/ovisbot.po
ovisbot-2.0.0.dist-info/LICENCE.md
ovisbot-2.0.0.dist-info/METADATA
ovisbot-2.0.0.dist-info/WHEEL
ovisbot-2.0.0.dist-info/entry_points.txt
ovisbot-2.0.0.dist-info/top_level.txt
ovisbot-2.0.0.dist-info/RECORD
