Metadata-Version: 2.1
Name: ovisbot
Version: 2.0.0
Summary: A modular Discord bot for CTF teams
Home-page: https://github.com/cybermouflons/ovisbot
Author: CYberMouflons
Author-email: info@cybermouflons.com
License: GPL-3.0
Platform: UNKNOWN
Classifier: Development Status :: 5 - Production/Stable
Classifier: Framework :: AsyncIO
Classifier: Framework :: Pytest
Classifier: Intended Audience :: Developers
Classifier: Intended Audience :: End Users/Desktop
Classifier: License :: OSI Approved :: GNU General Public License v3 (GPLv3)
Classifier: Natural Language :: English
Classifier: Operating System :: OS Independent
Classifier: Programming Language :: Python :: 3.7
Classifier: Topic :: Communications :: Chat
Classifier: Topic :: Documentation :: Sphinx
Requires-Python: >=3.7.0
